{"sections":{"AC2A":{"parent":"mille-plateaux/index","parent_specified":false,"references":["AC2C","AC2D","bib/blass2025choice"],"backlinks":[]},"AC2C":{"parent":"AC2A","parent_specified":false,"references":["AC2C"],"backlinks":["AC2A","AC2E"]},"AC2D":{"parent":"index","parent_specified":false,"references":[],"backlinks":[]},"AC2E":{"parent":"AC2A","parent_specified":false,"references":["AC2C"],"backlinks":["AC2A"]},"AP2A":{"parent":"index","parent_specified":false,"references":[],"backlinks":[]},"LF2A":{"parent":"index","parent_specified":false,"references":[],"backlinks":[]},"bib/blass1995seven":{"parent":"index","parent_specified":false,"references":[],"backlinks":["data-structure/blass-lawvere"]},"bib/blass2025choice":{"parent":"index","parent_specified":false,"references":[],"backlinks":["AC2A"]},"bib/hille1982stack":{"parent":"index","parent_specified":false,"references":[],"backlinks":["data-structure/stack-permutation/hille-encode","data-structure/stack-permutation/isomorphism"]},"bib/jin2024topos":{"parent":"index","parent_specified":false,"references":["bib/methods-of-algebra-1"],"backlinks":["data-structure/synthetic-differential/kock-lawvere"]},"bib/kock2006synthetic":{"parent":"index","parent_specified":false,"references":[],"backlinks":["data-structure/synthetic-differential/kock-lawvere"]},"bib/methods-of-algebra-1":{"parent":"index","parent_specified":false,"references":[],"backlinks":["bib/jin2024topos","data-structure/synthetic-differential/kock-lawvere"]},"bib/pftb":{"parent":"index","parent_specified":false,"references":[],"backlinks":["pearls/pftb-P005"]},"books":{"parent":"index","parent_specified":false,"references":[],"backlinks":["bib/pftb"]},"cc":{"parent":"index","parent_specified":false,"references":[],"backlinks":["linear-algebra/amtx"]},"contact":{"parent":"kokic","parent_specified":false,"references":[],"backlinks":[]},"cv":{"parent":"kokic","parent_specified":false,"references":[],"backlinks":[]},"daily-surf/HIRO":{"parent":"daily-surf/index","parent_specified":false,"references":[],"backlinks":[]},"daily-surf/SWSL":{"parent":"daily-surf/index","parent_specified":false,"references":[],"backlinks":[]},"daily-surf/adams":{"parent":"daily-surf/index","parent_specified":false,"references":[],"backlinks":[]},"daily-surf/baby-viewpoint":{"parent":"daily-surf/index","parent_specified":false,"references":[],"backlinks":[]},"daily-surf/bevy":{"parent":"daily-surf/index","parent_specified":false,"references":[],"backlinks":[]},"daily-surf/euclid-step":{"parent":"index","parent_specified":false,"references":[],"backlinks":[]},"daily-surf/fibonacci-flip":{"parent":"daily-surf/index","parent_specified":false,"references":[],"backlinks":[]},"daily-surf/file-transfer":{"parent":"daily-surf/index","parent_specified":false,"references":[],"backlinks":[]},"daily-surf/gaussian-integral":{"parent":"index","parent_specified":false,"references":[],"backlinks":[]},"daily-surf/git-filter-branch":{"parent":"daily-surf/index","parent_specified":false,"references":[],"backlinks":[]},"daily-surf/haskell":{"parent":"daily-surf/index","parent_specified":false,"references":[],"backlinks":[]},"daily-surf/index":{"parent":"index","parent_specified":false,"references":[],"backlinks":[]},"daily-surf/nvidia-fps-gpu-cpu":{"parent":"daily-surf/index","parent_specified":false,"references":[],"backlinks":[]},"daily-surf/sagemath-theme":{"parent":"daily-surf/index","parent_specified":false,"references":[],"backlinks":[]},"daily-surf/sublime-text-config":{"parent":"daily-surf/index","parent_specified":false,"references":[],"backlinks":[]},"daily-surf/windows-skill":{"parent":"daily-surf/index","parent_specified":false,"references":[],"backlinks":[]},"daily-surf/wolfram-engine":{"parent":"daily-surf/index","parent_specified":false,"references":[],"backlinks":[]},"data-structure/CG2A":{"parent":"index","parent_specified":false,"references":[],"backlinks":[]},"data-structure/binary-tree":{"parent":"data-structure/seven-trees-in-one","parent_specified":false,"references":[],"backlinks":[]},"data-structure/blass-lawvere":{"parent":"data-structure/seven-trees-in-one","parent_specified":false,"references":["bib/blass1995seven"],"backlinks":[]},"data-structure/complex-number":{"parent":"index","parent_specified":false,"references":[],"backlinks":[]},"data-structure/deletion-contraction":{"parent":"data-structure/CG2A","parent_specified":false,"references":[],"backlinks":["data-structure/CG2A"]},"data-structure/fiore-leinster":{"parent":"data-structure/blass-lawvere","parent_specified":false,"references":[],"backlinks":["data-structure/blass-lawvere"]},"data-structure/index":{"parent":"index","parent_specified":false,"references":[],"backlinks":[]},"data-structure/pratt":{"parent":"index","parent_specified":false,"references":[],"backlinks":[]},"data-structure/seven-trees-in-one":{"parent":"data-structure/index","parent_specified":false,"references":["bib/blass1995seven"],"backlinks":[]},"data-structure/stack-permutation/bounds":{"parent":"data-structure/stack-permutation/isomorphism","parent_specified":false,"references":[],"backlinks":[]},"data-structure/stack-permutation/bounds-pf":{"parent":"data-structure/stack-permutation/bounds","parent_specified":false,"references":[],"backlinks":[]},"data-structure/stack-permutation/equivalence":{"parent":"data-structure/stack-permutation/isomorphism","parent_specified":false,"references":[],"backlinks":["data-structure/stack-permutation/isomorphism"]},"data-structure/stack-permutation/equivalence-pf":{"parent":"data-structure/stack-permutation/equivalence","parent_specified":false,"references":[],"backlinks":[]},"data-structure/stack-permutation/hille-encode":{"parent":"data-structure/stack-permutation/isomorphism","parent_specified":false,"references":[],"backlinks":["data-structure/stack-permutation/equivalence-pf","data-structure/stack-permutation/isomorphism"]},"data-structure/stack-permutation/intersection":{"parent":"data-structure/stack-permutation/isomorphism","parent_specified":false,"references":[],"backlinks":["data-structure/stack-permutation/ratio"]},"data-structure/stack-permutation/isomorphism":{"parent":"data-structure/index","parent_specified":false,"references":["bib/hille1982stack"],"backlinks":[]},"data-structure/stack-permutation/ratio":{"parent":"data-structure/stack-permutation/isomorphism","parent_specified":false,"references":[],"backlinks":["data-structure/stack-permutation/isomorphism"]},"data-structure/stack-permutation/stack-permutation":{"parent":"data-structure/stack-permutation/isomorphism","parent_specified":false,"references":[],"backlinks":[]},"data-structure/stack-permutation/three-nodes":{"parent":"data-structure/stack-permutation/isomorphism","parent_specified":false,"references":[],"backlinks":["data-structure/stack-permutation/bounds"]},"data-structure/stern-brocot":{"parent":"index","parent_specified":false,"references":[],"backlinks":[]},"data-structure/synthetic-differential/chain-rule":{"parent":"data-structure/synthetic-differential/dual-number","parent_specified":false,"references":[],"backlinks":[]},"data-structure/synthetic-differential/complex-step":{"parent":"data-structure/synthetic-differential/index","parent_specified":false,"references":[],"backlinks":["data-structure/synthetic-differential/matrix-represent","data-structure/synthetic-differential/moler-correction"]},"data-structure/synthetic-differential/derived-differential":{"parent":"data-structure/synthetic-differential/dual-number","parent_specified":false,"references":[],"backlinks":["data-structure/synthetic-differential/chain-rule"]},"data-structure/synthetic-differential/dual-number":{"parent":"data-structure/synthetic-differential/index","parent_specified":false,"references":["bib/jin2024topos","bib/kock2006synthetic","bib/methods-of-algebra-1"],"backlinks":["data-structure/synthetic-differential/complex-step","data-structure/synthetic-differential/matrix-represent","data-structure/synthetic-differential/moler-correction"]},"data-structure/synthetic-differential/index":{"parent":"data-structure/index","parent_specified":false,"references":["bib/jin2024topos","bib/kock2006synthetic","bib/methods-of-algebra-1"],"backlinks":[]},"data-structure/synthetic-differential/kock-lawvere":{"parent":"data-structure/synthetic-differential/dual-number","parent_specified":false,"references":["bib/jin2024topos","bib/kock2006synthetic","bib/methods-of-algebra-1"],"backlinks":["data-structure/synthetic-differential/complex-step","data-structure/synthetic-differential/dual-number","data-structure/synthetic-differential/schanuel-lavendhomme","data-structure/synthetic-differential/smooths"]},"data-structure/synthetic-differential/matrix-represent":{"parent":"data-structure/synthetic-differential/dual-number","parent_specified":false,"references":[],"backlinks":["data-structure/synthetic-differential/moler-correction"]},"data-structure/synthetic-differential/moler-correction":{"parent":"data-structure/synthetic-differential/index","parent_specified":false,"references":[],"backlinks":["data-structure/synthetic-differential/matrix-represent"]},"data-structure/synthetic-differential/numerical":{"parent":"data-structure/synthetic-differential/index","parent_specified":false,"references":[],"backlinks":["data-structure/synthetic-differential/moler-correction"]},"data-structure/synthetic-differential/schanuel-lavendhomme":{"parent":"index","parent_specified":false,"references":[],"backlinks":["data-structure/synthetic-differential/dual-number"]},"data-structure/synthetic-differential/smooths":{"parent":"data-structure/synthetic-differential/kock-lawvere","parent_specified":false,"references":[],"backlinks":[]},"index":{"parent":"index","parent_specified":false,"references":[],"backlinks":[]},"kokic":{"parent":"index","parent_specified":false,"references":[],"backlinks":["AC2A","AP2A","LF2A","cv","daily-surf/SWSL","daily-surf/baby-viewpoint","daily-surf/bevy","daily-surf/euclid-step","daily-surf/fibonacci-flip","daily-surf/file-transfer","daily-surf/gaussian-integral","daily-surf/git-filter-branch","daily-surf/haskell","daily-surf/nvidia-fps-gpu-cpu","daily-surf/sagemath-theme","daily-surf/sublime-text-config","daily-surf/windows-skill","daily-surf/wolfram-engine","data-structure/CG2A","data-structure/binary-tree","data-structure/blass-lawvere","data-structure/complex-number","data-structure/deletion-contraction","data-structure/fiore-leinster","data-structure/seven-trees-in-one","data-structure/stack-permutation/bounds","data-structure/stack-permutation/bounds-pf","data-structure/stack-permutation/equivalence","data-structure/stack-permutation/equivalence-pf","data-structure/stack-permutation/intersection","data-structure/stack-permutation/isomorphism","data-structure/stack-permutation/ratio","data-structure/stack-permutation/stack-permutation","data-structure/stack-permutation/three-nodes","data-structure/stern-brocot","data-structure/synthetic-differential/chain-rule","data-structure/synthetic-differential/complex-step","data-structure/synthetic-differential/derived-differential","data-structure/synthetic-differential/dual-number","data-structure/synthetic-differential/index","data-structure/synthetic-differential/kock-lawvere","data-structure/synthetic-differential/matrix-represent","data-structure/synthetic-differential/moler-correction","data-structure/synthetic-differential/numerical","data-structure/synthetic-differential/schanuel-lavendhomme","data-structure/synthetic-differential/smooths","linear-algebra/amtx","linear-algebra/amtx-2A","linear-algebra/amtx-3A","linear-algebra/amtx-3B","linear-algebra/casus-irreducibilis","linear-algebra/conway-condition","linear-algebra/kontsevich-periodicity","linear-algebra/kontsevich-periodicity-2A","linear-algebra/permutation-matrix","linear-algebra/rayleigh-quotient","linear-algebra/rayleigh-quotient-2A","linear-algebra/rayleigh-quotient-2B","linear-algebra/rayleigh-quotient-3A","linear-algebra/regular-language","linear-algebra/semiring","linear-algebra/star-semiring","mille-plateaux/arc-length","mille-plateaux/bubble-compose","mille-plateaux/canterbury","mille-plateaux/canterbury-2A","mille-plateaux/canterbury-3A","mille-plateaux/circular-curve","mille-plateaux/circular-parameterization","mille-plateaux/elliptic-functions","mille-plateaux/elliptic-integral","mille-plateaux/fermat-ascent","mille-plateaux/laisant-young","mille-plateaux/periodic-2A","mille-plateaux/rational-points","pearls/CAN0","pearls/CHOW","pearls/CN2A","pearls/CN2B","pearls/CN2D","pearls/CN2E","pearls/CPSI","pearls/ECLA","pearls/GALA","pearls/GF2A","pearls/GF3A","pearls/HP2A","pearls/HP2B","pearls/HP2C","pearls/HP2D","pearls/HP2E","pearls/HP3A","pearls/SL2A","pearls/SL2B","pearls/YL2A","pearls/YL2B","pearls/YL3A","pearls/YL3B","pearls/YL3C","pearls/YL4A","pearls/pftb-P005","smaragdina/celtic-myths"]},"linear-algebra/AD2A":{"parent":"index","parent_specified":false,"references":["linear-algebra/AD2B"],"backlinks":[]},"linear-algebra/AD2B":{"parent":"index","parent_specified":false,"references":[],"backlinks":["linear-algebra/AD2A"]},"linear-algebra/AD2C":{"parent":"linear-algebra/AD2A","parent_specified":false,"references":[],"backlinks":[]},"linear-algebra/amtx":{"parent":"linear-algebra/index","parent_specified":false,"references":[],"backlinks":[]},"linear-algebra/amtx-2A":{"parent":"linear-algebra/amtx","parent_specified":false,"references":[],"backlinks":[]},"linear-algebra/amtx-3A":{"parent":"linear-algebra/amtx","parent_specified":false,"references":[],"backlinks":[]},"linear-algebra/amtx-3B":{"parent":"linear-algebra/amtx","parent_specified":false,"references":[],"backlinks":[]},"linear-algebra/casus-irreducibilis":{"parent":"index","parent_specified":false,"references":[],"backlinks":["data-structure/synthetic-differential/dual-number"]},"linear-algebra/conway-condition":{"parent":"index","parent_specified":false,"references":[],"backlinks":["linear-algebra/amtx-2A"]},"linear-algebra/index":{"parent":"index","parent_specified":false,"references":[],"backlinks":[]},"linear-algebra/kontsevich-periodicity":{"parent":"linear-algebra/index","parent_specified":false,"references":[],"backlinks":[]},"linear-algebra/kontsevich-periodicity-2A":{"parent":"linear-algebra/kontsevich-periodicity","parent_specified":false,"references":[],"backlinks":["linear-algebra/kontsevich-periodicity"]},"linear-algebra/permutation-matrix":{"parent":"linear-algebra/index","parent_specified":false,"references":[],"backlinks":[]},"linear-algebra/rayleigh-quotient":{"parent":"linear-algebra/index","parent_specified":false,"references":[],"backlinks":[]},"linear-algebra/rayleigh-quotient-2A":{"parent":"linear-algebra/rayleigh-quotient","parent_specified":false,"references":[],"backlinks":[]},"linear-algebra/rayleigh-quotient-2B":{"parent":"linear-algebra/rayleigh-quotient","parent_specified":false,"references":[],"backlinks":[]},"linear-algebra/rayleigh-quotient-3A":{"parent":"linear-algebra/rayleigh-quotient","parent_specified":false,"references":[],"backlinks":[]},"linear-algebra/regular-language":{"parent":"linear-algebra/amtx","parent_specified":false,"references":[],"backlinks":["linear-algebra/star-semiring"]},"linear-algebra/semiring":{"parent":"linear-algebra/amtx","parent_specified":false,"references":[],"backlinks":["linear-algebra/amtx-2A"]},"linear-algebra/star-semiring":{"parent":"linear-algebra/amtx","parent_specified":false,"references":[],"backlinks":[]},"links":{"parent":"kokic","parent_specified":false,"references":[],"backlinks":[]},"mille-plateaux/arc-length":{"parent":"index","parent_specified":false,"references":[],"backlinks":["mille-plateaux/circular-curve"]},"mille-plateaux/bubble-compose":{"parent":"index","parent_specified":false,"references":[],"backlinks":[]},"mille-plateaux/canterbury":{"parent":"mille-plateaux/rational-points","parent_specified":false,"references":[],"backlinks":[]},"mille-plateaux/canterbury-2A":{"parent":"mille-plateaux/canterbury","parent_specified":false,"references":[],"backlinks":["mille-plateaux/canterbury","mille-plateaux/canterbury-3A"]},"mille-plateaux/canterbury-3A":{"parent":"mille-plateaux/canterbury","parent_specified":false,"references":[],"backlinks":[]},"mille-plateaux/circular-curve":{"parent":"mille-plateaux/rational-points","parent_specified":false,"references":[],"backlinks":["mille-plateaux/periodic-2A"]},"mille-plateaux/circular-parameterization":{"parent":"mille-plateaux/rational-points","parent_specified":false,"references":[],"backlinks":["mille-plateaux/circular-curve"]},"mille-plateaux/elliptic-functions":{"parent":"index","parent_specified":false,"references":[],"backlinks":["mille-plateaux/circular-curve"]},"mille-plateaux/elliptic-integral":{"parent":"index","parent_specified":false,"references":[],"backlinks":["mille-plateaux/circular-curve"]},"mille-plateaux/fermat-ascent":{"parent":"mille-plateaux/canterbury","parent_specified":false,"references":[],"backlinks":[]},"mille-plateaux/index":{"parent":"index","parent_specified":false,"references":[],"backlinks":[]},"mille-plateaux/j-invariant":{"parent":"index","parent_specified":false,"references":[],"backlinks":[]},"mille-plateaux/laisant-young":{"parent":"index","parent_specified":false,"references":[],"backlinks":[]},"mille-plateaux/periodic-2A":{"parent":"mille-plateaux/index","parent_specified":false,"references":[],"backlinks":[]},"mille-plateaux/periodic-2B":{"parent":"mille-plateaux/periodic-2A","parent_specified":false,"references":[],"backlinks":[]},"mille-plateaux/periodic-2C":{"parent":"mille-plateaux/periodic-2A","parent_specified":false,"references":[],"backlinks":[]},"mille-plateaux/q-denote":{"parent":"index","parent_specified":false,"references":[],"backlinks":["mille-plateaux/j-invariant"]},"mille-plateaux/rational-points":{"parent":"mille-plateaux/index","parent_specified":false,"references":[],"backlinks":[]},"pearls/CAN0":{"parent":"index","parent_specified":false,"references":[],"backlinks":[]},"pearls/CHOW":{"parent":"index","parent_specified":false,"references":[],"backlinks":[]},"pearls/CN2A":{"parent":"index","parent_specified":false,"references":["pearls/CN2C","pearls/SL2A"],"backlinks":["pearls/CN2D","pearls/HP2E"]},"pearls/CN2B":{"parent":"pearls/CN2A","parent_specified":false,"references":[],"backlinks":["pearls/CN2C","pearls/CN2D","pearls/CN2E","pearls/HP2A","pearls/HP2C"]},"pearls/CN2C":{"parent":"pearls/CN2A","parent_specified":false,"references":[],"backlinks":["pearls/CN2E","pearls/HP2A","pearls/HP2D"]},"pearls/CN2D":{"parent":"pearls/CN2A","parent_specified":false,"references":[],"backlinks":["pearls/HP2C"]},"pearls/CN2E":{"parent":"pearls/CN2A","parent_specified":false,"references":["pearls/CN2C"],"backlinks":[]},"pearls/CNA1":{"parent":"pearls/CAN0","parent_specified":false,"references":[],"backlinks":["pearls/CAN0"]},"pearls/CPSI":{"parent":"index","parent_specified":false,"references":[],"backlinks":[]},"pearls/ECLA":{"parent":"index","parent_specified":false,"references":[],"backlinks":[]},"pearls/GALA":{"parent":"index","parent_specified":false,"references":[],"backlinks":[]},"pearls/GF2A":{"parent":"index","parent_specified":false,"references":["pearls/GF3A"],"backlinks":[]},"pearls/GF3A":{"parent":"index","parent_specified":false,"references":[],"backlinks":["pearls/GF2A"]},"pearls/HP2A":{"parent":"index","parent_specified":false,"references":["pearls/CN2C","pearls/HP2B","pearls/SL2A"],"backlinks":["pearls/HP2B","pearls/HP2C","pearls/HP2E"]},"pearls/HP2B":{"parent":"index","parent_specified":false,"references":["pearls/HP2A"],"backlinks":["pearls/HP2A","pearls/HP2D","pearls/HP3A"]},"pearls/HP2C":{"parent":"index","parent_specified":false,"references":["pearls/HP2A"],"backlinks":["pearls/HP2D","pearls/HP2E"]},"pearls/HP2D":{"parent":"index","parent_specified":false,"references":["pearls/CN2C","pearls/HP2B","pearls/HP2C","pearls/SL2A"],"backlinks":[]},"pearls/HP2E":{"parent":"index","parent_specified":false,"references":["pearls/HP2A","pearls/HP2B","pearls/HP2C","pearls/HP2D","pearls/SL2A"],"backlinks":["pearls/HP2D"]},"pearls/HP3A":{"parent":"index","parent_specified":false,"references":["pearls/HP2B"],"backlinks":[]},"pearls/SL2A":{"parent":"index","parent_specified":false,"references":[],"backlinks":["pearls/CN2A","pearls/HP2A","pearls/HP2D","pearls/HP2E"]},"pearls/SL2B":{"parent":"index","parent_specified":false,"references":[],"backlinks":[]},"pearls/YL2A":{"parent":"index","parent_specified":false,"references":["pearls/YL2B"],"backlinks":[]},"pearls/YL2B":{"parent":"pearls/YL2A","parent_specified":false,"references":[],"backlinks":["pearls/YL2A","pearls/YL3A","pearls/YL3B","pearls/YL3C"]},"pearls/YL3A":{"parent":"pearls/YL2A","parent_specified":false,"references":["pearls/YL2B"],"backlinks":["pearls/YL2A","pearls/YL4A"]},"pearls/YL3B":{"parent":"pearls/YL2A","parent_specified":false,"references":["pearls/YL2B"],"backlinks":["pearls/CPSI"]},"pearls/YL3C":{"parent":"pearls/YL2A","parent_specified":false,"references":["pearls/YL2B"],"backlinks":[]},"pearls/YL4A":{"parent":"index","parent_specified":false,"references":[],"backlinks":["mille-plateaux/laisant-young","pearls/YL2A"]},"pearls/index":{"parent":"index","parent_specified":false,"references":[],"backlinks":["daily-surf/euclid-step","daily-surf/gaussian-integral","data-structure/deletion-contraction","mille-plateaux/bubble-compose","mille-plateaux/canterbury-2A","pearls/CAN0","pearls/CHOW","pearls/CN2A","pearls/CPSI","pearls/ECLA","pearls/GALA","pearls/GF2A","pearls/GF3A","pearls/HP2E","pearls/YL2A","pearls/pftb-P005"]},"pearls/pftb-P005":{"parent":"index","parent_specified":false,"references":["bib/pftb"],"backlinks":[]},"person/dustin-clausen":{"parent":"index","parent_specified":false,"references":[],"backlinks":[]},"person/ernst-kummer":{"parent":"index","parent_specified":false,"references":[],"backlinks":["daily-surf/baby-viewpoint","data-structure/CG2A"]},"person/george-david-birkhoff":{"parent":"index","parent_specified":false,"references":[],"backlinks":["data-structure/CG2A"]},"person/william-lawvere":{"parent":"index","parent_specified":false,"references":[],"backlinks":["data-structure/synthetic-differential/kock-lawvere"]},"person/yuni":{"parent":"index","parent_specified":false,"references":[],"backlinks":["daily-surf/adams"]},"smaragdina/celtic-myths":{"parent":"smaragdina/index","parent_specified":false,"references":[],"backlinks":[]},"smaragdina/flat-structuralism":{"parent":"index","parent_specified":false,"references":[],"backlinks":[]},"smaragdina/index":{"parent":"index","parent_specified":false,"references":[],"backlinks":[]},"smaragdina/lynch-movie":{"parent":"smaragdina/index","parent_specified":false,"references":[],"backlinks":[]},"stocking":{"parent":"AC2C","parent_specified":false,"references":[],"backlinks":[]}}}